{
  "name": "People",
  "base": "PersistedModel",
  "idInjection": false,
  "options": {
    "validateUpsert": true
  },
  "mysql": {
    "schema": "mydb",
    "table": "people"
  },
  "properties": {
    "emailid": {
      "type": "String",
      "id": true,
      "required": true,
      "index": true,
      "length": 255,
      "precision": null,
      "scale": null,
      "mysql": {
        "columnName": "emailid",
        "dataType": "char",
        "dataLength": 255,
        "dataPrecision": null,
        "dataScale": null,
        "nullable": "N"
      }
    },
    "password": {
      "type": "String",
      "required": true,
      "length": 255,
      "precision": null,
      "scale": null,
      "mysql": {
        "columnName": "password",
        "dataType": "varchar",
        "dataLength": 255,
        "dataPrecision": null,
        "dataScale": null,
        "nullable": "N"
      }
    },
    "username": {
      "type": "String",
      "required": false,
      "length": 45,
      "precision": null,
      "scale": null,
      "mysql": {
        "columnName": "username",
        "dataType": "varchar",
        "dataLength": 45,
        "dataPrecision": null,
        "dataScale": null,
        "nullable": "N"
      }
    }
  },
  "validations": [],
  "relations": {},
  "acls": [],
  "methods": {}
}
